protocol_proxy/protocol/bacnet/__init__.py
protocol_proxy/protocol/bacnet/bacnet.py
protocol_proxy/protocol/bacnet/bacnet_broadcast.py
protocol_proxy/protocol/bacnet/bacnet_proxy.py
protocol_proxy/protocol/bacnet/bacnet_utils.py
protocol_proxy/protocol/bacnet/cache_handler.py
protocol_proxy/protocol/bacnet/json.py
protocol_proxy_bacnet-2.0.0rc2.dist-info/LICENSE
protocol_proxy_bacnet-2.0.0rc2.dist-info/METADATA
protocol_proxy_bacnet-2.0.0rc2.dist-info/WHEEL
protocol_proxy_bacnet-2.0.0rc2.dist-info/RECORD
