Metadata-Version: 2.3
Name: protocol-proxy-bacnet
Version: 2.0.0rc2
Summary: A BACnet Protocol Proxy implementation. A BACnet Manager is provided which can launch proxy devices for communication with a BACnet network.
License: Apache-2.0
Author: The VOLTTRON Development Team
Author-email: volttron@pnnl.gov
Requires-Python: >=3.10,<4.0
Classifier: Intended Audience :: Developers
Classifier: Intended Audience :: Information Technology
Classifier: Intended Audience :: Other Audience
Classifier: Intended Audience :: Science/Research
Classifier: License :: OSI Approved :: Apache Software License
Classifier: Programming Language :: Python :: 3
Classifier: Programming Language :: Python :: 3.10
Classifier: Programming Language :: Python :: 3.11
Classifier: Programming Language :: Python :: 3.12
Classifier: Programming Language :: Python :: 3.13
Classifier: Programming Language :: Python :: 3 :: Only
Requires-Dist: bacpypes3 (>=0.0.102)
Requires-Dist: protocol-proxy (>=2.0.0rc0)
Project-URL: Homepage, https://github.com/eclipse-volttron/lib-protocol-proxy-bacnet
Project-URL: Repository, https://github.com/eclipse-volttron/lib-protocol-proxy-bacnet
